.coveragerc
.travis.yml
AUTHORS.rst
CHANGELOG.rst
CONTRIBUTING.rst
LICENSE
MANIFEST.in
README.rst
appveyor.yml
setup.cfg
setup.py
tox.ini
ci/appveyor-bootstrap.ps1
ci/appveyor-with-compiler.cmd
ci/bootstrap.py
ci/templates/.travis.yml
ci/templates/appveyor.yml
ci/templates/tox.ini
docs/authors.rst
docs/changelog.rst
docs/conf.py
docs/contributing.rst
docs/index.rst
docs/installation.rst
docs/readme.rst
docs/requirements.txt
docs/spelling_wordlist.txt
docs/usage.rst
docs/reference/index.rst
docs/reference/localsrv.rst
src/django_localsrv.egg-info/PKG-INFO
src/django_localsrv.egg-info/SOURCES.txt
src/django_localsrv.egg-info/dependency_links.txt
src/django_localsrv.egg-info/entry_points.txt
src/django_localsrv.egg-info/not-zip-safe
src/django_localsrv.egg-info/requires.txt
src/django_localsrv.egg-info/top_level.txt
src/localsrv/__init__.py
src/localsrv/admin.py
src/localsrv/db.sqlite3
src/localsrv/forms.py
src/localsrv/models.py
src/localsrv/services.py
src/localsrv/test_settings.py
src/localsrv/test_urls.py
src/localsrv/tests.py
src/localsrv/urls.py
src/localsrv/views.py
src/localsrv/migrations/0001_initial.py
src/localsrv/migrations/__init__.py
tests/test_localsrv.py