Metadata-Version: 1.1
Name: django-localsrv
Version: 0.1.2
Summary: Django app for serving static content from different sources (files, strings, urls, etc.) at custom paths, using custom HTTP headers. Intended as a more flexible option than Python's SimpleHTTPServer
Home-page: https://github.com/vladiibine/localsrv
Author: Vlad George Ardelean
Author-email: asdf@yopmail.com
License: MIT
Platform: UNKNOWN
Classifier: Development Status :: 1 - Planning
Classifier: Intended Audience :: Developers
Classifier: License :: OSI Approved :: MIT License
Classifier: Operating System :: Unix
Classifier: Operating System :: POSIX
Classifier: Operating System :: Microsoft :: Windows
Classifier: Programming Language :: Python
Classifier: Programming Language :: Python :: 2.6
Classifier: Programming Language :: Python :: 2.7
Classifier: Programming Language :: Python :: 3
Classifier: Programming Language :: Python :: 3.3
Classifier: Programming Language :: Python :: 3.4
Classifier: Programming Language :: Python :: Implementation :: CPython
Classifier: Programming Language :: Python :: Implementation :: PyPy
Classifier: Topic :: Utilities
Classifier: Topic :: Internet :: WWW/HTTP :: HTTP Servers
